README.md
setup.cfg
setup.py
SarcLib/FileArchive.py
SarcLib/__init__.py
SarcLib.egg-info/PKG-INFO
SarcLib.egg-info/SOURCES.txt
SarcLib.egg-info/dependency_links.txt
SarcLib.egg-info/top_level.txt