Metadata-Version: 1.1
Name: SarcLib
Version: 0.3
Summary: A library for handling the Nintendo SARC archive format
Home-page: https://github.com/aboood40091/SarcLib
Author: AboodXD
Author-email: aboood40091@gmail.com
License: GNU General Public License v3 (GPLv3)
Download-URL: https://github.com/aboood40091/SarcLib/archive/v0.3.tar.gz
Keywords: arc,sarc,szs,yaz0
Platform: UNKNOWN
Classifier: License :: OSI Approved :: GNU General Public License v3 (GPLv3)
Classifier: Programming Language :: Python :: 3 :: Only
Classifier: Topic :: Software Development :: Libraries :: Python Modules
Classifier: Topic :: System :: Archiving
